allpowers_ble/__init__.py
allpowers_ble/allpowers_ble.py
allpowers_ble/exceptions.py
allpowers_ble/models.py
allpowers_ble/py.typed
allpowers_ble/run.py
allpowers_ble-0.0.2.dist-info/LICENSE
allpowers_ble-0.0.2.dist-info/METADATA
allpowers_ble-0.0.2.dist-info/WHEEL
allpowers_ble-0.0.2.dist-info/RECORD
