Metadata-Version: 2.1
Name: allpowers-ble
Version: 0.0.2
Summary: Interface with smart batteries from Allpowers
Home-page: https://github.com/madninjaskillz/allpowers-ble
License: MIT
Author: James Johnston
Author-email: james@ezmuze.co.uk
Requires-Python: >=3.8,<4.0
Classifier: Development Status :: 2 - Pre-Alpha
Classifier: Intended Audience :: Developers
Classifier: License :: OSI Approved :: MIT License
Classifier: Natural Language :: English
Classifier: Operating System :: OS Independent
Classifier: Programming Language :: Python :: 3
Classifier: Programming Language :: Python :: 3.8
Classifier: Programming Language :: Python :: 3.9
Classifier: Programming Language :: Python :: 3.10
Classifier: Programming Language :: Python :: 3.11
Classifier: Topic :: Software Development :: Libraries
Project-URL: Bug Tracker, https://github.com/madninjaskillz/allpowers-ble/issues
Project-URL: Changelog, https://github.com/madninjaskillz/allpowers-ble/blob/main/CHANGELOG.md
Project-URL: Documentation, https://allpowers-ble.readthedocs.io
Project-URL: Repository, https://github.com/madninjaskillz/allpowers-ble
